[{"time": "2026-04-01 16:38:58", "callsign": "N8JEW", "tg_slot": "93"}, {"time": "2026-04-01 16:38:49", "callsign": "KE4LNG", "tg_slot": "93"}, {"time": "2026-04-01 16:38:20", "callsign": "N8JEW", "tg_slot": "93"}, {"time": "2026-04-01 16:38:10", "callsign": "KE4LNG", "tg_slot": "93"}, {"time": "2026-04-01 16:37:32", "callsign": "KE4LNG", "tg_slot": "93"}, {"time": "2026-04-01 16:37:23", "callsign": "N8JEW", "tg_slot": "93"}, {"time": "2026-04-01 16:37:14", "callsign": "KE4LNG", "tg_slot": "93"}, {"time": "2026-04-01 16:36:36", "callsign": "N8JEW", "tg_slot": "93"}, {"time": "2026-04-01 16:36:23", "callsign": "WB4FCU", "tg_slot": "93"}, {"time": "2026-04-01 16:36:03", "callsign": "KE4LNG", "tg_slot": "93"}, {"time": "2026-04-01 16:35:47", "callsign": "KE0CBT", "tg_slot": "93"}, {"time": "2026-04-01 16:35:04", "callsign": "KE4LNG", "tg_slot": "93"}, {"time": "2026-04-01 16:34:49", "callsign": "KE4LNG", "tg_slot": "93"}, {"time": "2026-04-01 16:30:40", "callsign": "W2AH", "tg_slot": "93"}]