[{"time": "2026-03-17 15:45:01", "callsign": "VU3DEE", "tg_slot": "93"}, {"time": "2026-03-17 15:44:55", "callsign": "KG5LXV", "tg_slot": "93"}, {"time": "2026-03-17 15:43:14", "callsign": "VU3DOU", "tg_slot": "93"}, {"time": "2026-03-17 15:43:00", "callsign": "VU3DEE", "tg_slot": "93"}, {"time": "2026-03-17 15:42:45", "callsign": "VU3DOU", "tg_slot": "93"}, {"time": "2026-03-17 15:42:21", "callsign": "VU3DEE", "tg_slot": "93"}, {"time": "2026-03-17 15:41:51", "callsign": "VU3DOU", "tg_slot": "93"}, {"time": "2026-03-17 15:40:45", "callsign": "VU3DEE", "tg_slot": "93"}, {"time": "2026-03-17 15:40:28", "callsign": "VU3DOU", "tg_slot": "93"}, {"time": "2026-03-17 15:40:00", "callsign": "VU3DEE", "tg_slot": "93"}, {"time": "2026-03-17 15:39:55", "callsign": "VU3DOU", "tg_slot": "93"}, {"time": "2026-03-17 15:39:44", "callsign": "VU3DEE", "tg_slot": "93"}, {"time": "2026-03-17 15:39:36", "callsign": "VU3DOU", "tg_slot": "93"}, {"time": "2026-03-17 15:39:26", "callsign": "VU3DEE", "tg_slot": "93"}, {"time": "2026-03-17 15:39:22", "callsign": "VU3DOU", "tg_slot": "93"}, {"time": "2026-03-17 15:39:19", "callsign": "VU3DOU", "tg_slot": "93"}, {"time": "2026-03-17 15:39:17", "callsign": "VU3DOU", "tg_slot": "93"}, {"time": "2026-03-17 15:38:45", "callsign": "I2JWK", "tg_slot": "93"}]