[{"time": "2026-03-19 23:39:56", "callsign": "EA1BDV", "tg_slot": "93"}, {"time": "2026-03-19 23:39:41", "callsign": "K2TPT", "tg_slot": "93"}, {"time": "2026-03-19 23:39:13", "callsign": "KB6JSM", "tg_slot": "93"}, {"time": "2026-03-19 23:39:04", "callsign": "EA1BDV", "tg_slot": "93"}, {"time": "2026-03-19 23:38:32", "callsign": "EA1BDV", "tg_slot": "93"}, {"time": "2026-03-19 23:38:16", "callsign": "EA1BDV", "tg_slot": "93"}, {"time": "2026-03-19 23:35:37", "callsign": "KF5WFA", "tg_slot": "93"}, {"time": "2026-03-19 23:35:23", "callsign": "KB8KKV", "tg_slot": "93"}, {"time": "2026-03-19 23:34:47", "callsign": "KB8KKV", "tg_slot": "93"}, {"time": "2026-03-19 23:27:48", "callsign": "VA3KY", "tg_slot": "93"}, {"time": "2026-03-19 23:23:44", "callsign": "AB7P", "tg_slot": "93"}, {"time": "2026-03-19 23:22:54", "callsign": "W3HRD", "tg_slot": "93"}, {"time": "2026-03-19 23:22:33", "callsign": "K2TPT", "tg_slot": "93"}, {"time": "2026-03-19 23:19:35", "callsign": "K2TPT", "tg_slot": "93"}]