{"entries": [{"time": "2026-04-20 00:04:41", "callsign": "KM7ENH", "tg_slot": "93"}, {"time": "2026-04-20 00:03:49", "callsign": "K2TPT", "tg_slot": "93"}, {"time": "2026-04-20 00:02:59", "callsign": "KM7ENH", "tg_slot": "93"}, {"time": "2026-04-20 00:02:13", "callsign": "K2TPT", "tg_slot": "93"}, {"time": "2026-04-20 00:00:51", "callsign": "KM7ENH", "tg_slot": "93"}, {"time": "2026-04-20 00:00:21", "callsign": "K2TPT", "tg_slot": "93"}], "system": {"hostname": "pi-star", "uptime": "up 6 weeks, 6 days, 9 hours, 55 minutes", "cpu_load": 0.24, "temperature": "temp=49.9'C", "memory": "150/972 MB", "disk": "4.4G/119G (4%)"}}