{"entries": [{"time": "2026-04-24 05:49:46", "callsign": "KC2VAB", "tg_slot": "93"}, {"time": "2026-04-24 05:43:51", "callsign": "KT7JOE", "tg_slot": "93"}, {"time": "2026-04-24 05:37:55", "callsign": "K0SPY", "tg_slot": "6"}, {"time": "2026-04-24 05:25:06", "callsign": "VK6KHZ", "tg_slot": "93"}, {"time": "2026-04-24 05:23:20", "callsign": "KT7JOE", "tg_slot": "93"}, {"time": "2026-04-24 05:14:36", "callsign": "W0RS", "tg_slot": "93"}, {"time": "2026-04-24 05:10:32", "callsign": "KO6MPS", "tg_slot": "93"}, {"time": "2026-04-24 05:06:58", "callsign": "KT7JOE", "tg_slot": "93"}, {"time": "2026-04-24 05:04:49", "callsign": "KT7JOE", "tg_slot": "93"}, {"time": "2026-04-24 04:56:30", "callsign": "N2DBQ", "tg_slot": "93"}, {"time": "2026-04-24 04:54:49", "callsign": "KB9YCZ", "tg_slot": "93"}, {"time": "2026-04-24 04:54:37", "callsign": "KO6JFF", "tg_slot": "93"}], "system": {"hostname": "pi-star", "uptime": "up 7 weeks, 3 days, 15 hours, 45 minutes", "cpu_load": 0.08, "temperature": "temp=50.5'C", "memory": "151/972 MB", "disk": "4.5G/119G (4%)"}}