[{"time": "2026-03-24 20:23:53", "callsign": "W7PCT", "tg_slot": "93"}, {"time": "2026-03-24 20:23:26", "callsign": "KK7CXS", "tg_slot": "93"}, {"time": "2026-03-24 20:23:24", "callsign": "KE2YK", "tg_slot": "93"}, {"time": "2026-03-24 20:23:11", "callsign": "W7PCT", "tg_slot": "93"}, {"time": "2026-03-24 20:23:01", "callsign": "KK7CXS", "tg_slot": "93"}, {"time": "2026-03-24 20:22:47", "callsign": "KK7CXS", "tg_slot": "93"}, {"time": "2026-03-24 20:22:39", "callsign": "W7PCT", "tg_slot": "93"}, {"time": "2026-03-24 20:22:05", "callsign": "KK7CXS", "tg_slot": "93"}, {"time": "2026-03-24 20:21:46", "callsign": "W7PCT", "tg_slot": "93"}, {"time": "2026-03-24 20:21:29", "callsign": "KK7CXS", "tg_slot": "93"}, {"time": "2026-03-24 20:21:23", "callsign": "KK7CXS", "tg_slot": "93"}, {"time": "2026-03-24 20:21:17", "callsign": "KK7CXS", "tg_slot": "93"}, {"time": "2026-03-24 20:21:08", "callsign": "W7PCT", "tg_slot": "93"}, {"time": "2026-03-24 20:20:38", "callsign": "KK7CXS", "tg_slot": "93"}, {"time": "2026-03-24 20:19:44", "callsign": "W7PCT", "tg_slot": "93"}, {"time": "2026-03-24 20:16:42", "callsign": "WO8L", "tg_slot": "93"}]