{"entries": [{"time": "2026-05-19 01:56:10", "callsign": "W3SGT", "tg_slot": "6"}, {"time": "2026-05-19 01:55:11", "callsign": "KC1DCZ", "tg_slot": "6"}, {"time": "2026-05-19 01:54:51", "callsign": "KC1DCZ", "tg_slot": "6"}, {"time": "2026-05-19 01:54:47", "callsign": "KC1DCZ", "tg_slot": "6"}, {"time": "2026-05-19 01:49:35", "callsign": "KJ5PSN", "tg_slot": "93"}, {"time": "2026-05-19 01:48:28", "callsign": "KJ4BZ", "tg_slot": "93"}, {"time": "2026-05-19 01:47:04", "callsign": "WP4TUY", "tg_slot": "93"}, {"time": "2026-05-19 01:43:05", "callsign": "KJ4BZ", "tg_slot": "93"}, {"time": "2026-05-19 01:39:28", "callsign": "KC8BT", "tg_slot": "93"}, {"time": "2026-05-19 01:39:23", "callsign": "KR4JBL", "tg_slot": "93"}, {"time": "2026-05-19 01:39:15", "callsign": "KR4JBL", "tg_slot": "93"}, {"time": "2026-05-19 01:39:13", "callsign": "KG6OMB", "tg_slot": "93"}, {"time": "2026-05-19 01:39:03", "callsign": "KG6OMB", "tg_slot": "93"}, {"time": "2026-05-19 01:38:57", "callsign": "KR4DXL", "tg_slot": "93"}, {"time": "2026-05-19 01:38:45", "callsign": "KR4DXL", "tg_slot": "93"}], "system": {"hostname": "pi-star", "uptime": "up 11 weeks, 11 hours, 50 minutes", "cpu_load": 0.18, "temperature": "temp=50.5'C", "memory": "152/972 MB", "disk": "4.4G/119G (4%)"}}