[{"time": "2026-03-26 20:34:53", "callsign": "KE0CBT", "tg_slot": "93"}, {"time": "2026-03-26 20:34:07", "callsign": "KA9QJH", "tg_slot": "93"}, {"time": "2026-03-26 20:28:11", "callsign": "MM3RCR", "tg_slot": "93"}, {"time": "2026-03-26 20:23:50", "callsign": "KF0GBZ", "tg_slot": "93"}, {"time": "2026-03-26 20:23:07", "callsign": "K1WTT", "tg_slot": "93"}, {"time": "2026-03-26 20:22:30", "callsign": "WB9PHK", "tg_slot": "93"}, {"time": "2026-03-26 20:08:52", "callsign": "AC6JA", "tg_slot": "93"}, {"time": "2026-03-26 20:08:26", "callsign": "WB9PHK", "tg_slot": "93"}, {"time": "2026-03-26 20:04:48", "callsign": "WB9PHK", "tg_slot": "93"}, {"time": "2026-03-26 20:04:23", "callsign": "WB9PHK", "tg_slot": "93"}, {"time": "2026-03-26 20:04:08", "callsign": "WB9PHK", "tg_slot": "93"}, {"time": "2026-03-26 20:04:04", "callsign": "WB9PHK", "tg_slot": "93"}, {"time": "2026-03-26 20:02:20", "callsign": "N3UAS", "tg_slot": "93"}]