{"entries": [{"time": "2026-06-05 02:14:36", "callsign": "KD1IX", "tg_slot": "93"}, {"time": "2026-06-05 02:14:28", "callsign": "KD1IX", "tg_slot": "93"}, {"time": "2026-06-05 02:14:09", "callsign": "N8KJT", "tg_slot": "93"}, {"time": "2026-06-05 02:13:27", "callsign": "KD1IX", "tg_slot": "93"}, {"time": "2026-06-05 02:12:55", "callsign": "N8KJT", "tg_slot": "93"}, {"time": "2026-06-05 02:10:16", "callsign": "KD1IX", "tg_slot": "93"}, {"time": "2026-06-05 02:08:04", "callsign": "W8OUG", "tg_slot": "93"}, {"time": "2026-06-05 02:07:59", "callsign": "KE2BCX", "tg_slot": "93"}, {"time": "2026-06-05 02:07:55", "callsign": "KR4LPI", "tg_slot": "93"}, {"time": "2026-06-05 02:07:35", "callsign": "KR4LPI", "tg_slot": "93"}, {"time": "2026-06-05 02:07:18", "callsign": "KR4LPI", "tg_slot": "93"}, {"time": "2026-06-05 02:07:01", "callsign": "KE2IIG", "tg_slot": "93"}, {"time": "2026-06-05 02:06:46", "callsign": "KE2IIG", "tg_slot": "93"}, {"time": "2026-06-05 02:04:52", "callsign": "KR4LPI", "tg_slot": "93"}, {"time": "2026-06-05 02:03:48", "callsign": "W2BDM", "tg_slot": "93"}], "system": {"hostname": "pi-star", "uptime": "up 13 weeks, 3 days, 12 hours, 5 minutes", "cpu_load": 0.02, "temperature": "temp=50.5'C", "memory": "151/972 MB", "disk": "4.4G/119G (4%)"}}