{"entries": [{"time": "2026-05-24 20:29:15", "callsign": "WZ4BSS", "tg_slot": "93"}, {"time": "2026-05-24 20:28:40", "callsign": "GM0MRJ", "tg_slot": "93"}, {"time": "2026-05-24 20:28:16", "callsign": "WZ4BSS", "tg_slot": "93"}, {"time": "2026-05-24 20:27:36", "callsign": "AB7P", "tg_slot": "93"}, {"time": "2026-05-24 20:26:26", "callsign": "WZ4BSS", "tg_slot": "93"}, {"time": "2026-05-24 20:25:37", "callsign": "KH6EKD", "tg_slot": "93"}, {"time": "2026-05-24 20:25:31", "callsign": "AB7P", "tg_slot": "93"}, {"time": "2026-05-24 20:23:53", "callsign": "WZ4BSS", "tg_slot": "93"}, {"time": "2026-05-24 20:23:25", "callsign": "AB7P", "tg_slot": "93"}, {"time": "2026-05-24 20:23:08", "callsign": "KJ5PSN", "tg_slot": "93"}, {"time": "2026-05-24 20:23:00", "callsign": "WZ4BSS", "tg_slot": "93"}, {"time": "2026-05-24 20:22:22", "callsign": "AB7P", "tg_slot": "93"}, {"time": "2026-05-24 20:22:00", "callsign": "AB7P", "tg_slot": "93"}, {"time": "2026-05-24 20:18:50", "callsign": "WA2LAN", "tg_slot": "93"}, {"time": "2026-05-24 20:17:38", "callsign": "NB9D", "tg_slot": "6"}], "system": {"hostname": "pi-star", "uptime": "up 11 weeks, 6 days, 6 hours, 20 minutes", "cpu_load": 0.09, "temperature": "temp=48.3'C", "memory": "151/972 MB", "disk": "4.4G/119G (4%)"}}