[{"time": "2026-03-21 00:09:35", "callsign": "KD3AHS", "tg_slot": "93"}, {"time": "2026-03-21 00:09:07", "callsign": "KE4UYD", "tg_slot": "93"}, {"time": "2026-03-21 00:08:57", "callsign": "W1VM", "tg_slot": "93"}, {"time": "2026-03-21 00:08:00", "callsign": "KD3AHS", "tg_slot": "93"}, {"time": "2026-03-21 00:07:36", "callsign": "W1VM", "tg_slot": "93"}, {"time": "2026-03-21 00:07:26", "callsign": "W1VM", "tg_slot": "93"}, {"time": "2026-03-21 00:07:14", "callsign": "KD3AHS", "tg_slot": "93"}, {"time": "2026-03-21 00:06:44", "callsign": "W1VM", "tg_slot": "93"}, {"time": "2026-03-21 00:05:55", "callsign": "KD3AHS", "tg_slot": "93"}, {"time": "2026-03-21 00:04:53", "callsign": "W1VM", "tg_slot": "93"}, {"time": "2026-03-21 00:04:32", "callsign": "KD3AHS", "tg_slot": "93"}, {"time": "2026-03-21 00:03:28", "callsign": "W1VM", "tg_slot": "93"}, {"time": "2026-03-21 00:02:50", "callsign": "KD3AHS", "tg_slot": "93"}, {"time": "2026-03-21 00:02:11", "callsign": "W1VM", "tg_slot": "93"}, {"time": "2026-03-21 00:01:48", "callsign": "KD3AHS", "tg_slot": "93"}, {"time": "2026-03-21 00:00:33", "callsign": "KD3AHS", "tg_slot": "93"}]