{"entries": [{"time": "2026-04-29 11:14:55", "callsign": "M1DFM", "tg_slot": "91"}, {"time": "2026-04-29 11:14:50", "callsign": "VU3LCE", "tg_slot": "91"}, {"time": "2026-04-29 11:14:16", "callsign": "LX1GQ", "tg_slot": "91"}, {"time": "2026-04-29 11:14:02", "callsign": "M9NJL", "tg_slot": "91"}, {"time": "2026-04-29 11:13:43", "callsign": "AI4TM", "tg_slot": "91"}, {"time": "2026-04-29 11:13:08", "callsign": "VU3LCE", "tg_slot": "91"}, {"time": "2026-04-29 11:13:01", "callsign": "M9NJL", "tg_slot": "91"}, {"time": "2026-04-29 11:12:33", "callsign": "AI4TM", "tg_slot": "91"}, {"time": "2026-04-29 11:12:11", "callsign": "M9NJL", "tg_slot": "91"}, {"time": "2026-04-29 11:11:54", "callsign": "M9NJL", "tg_slot": "91"}, {"time": "2026-04-29 11:11:41", "callsign": "VU2EHB", "tg_slot": "91"}, {"time": "2026-04-29 11:11:31", "callsign": "AI4TM", "tg_slot": "91"}, {"time": "2026-04-29 11:11:05", "callsign": "VU2EHB", "tg_slot": "91"}, {"time": "2026-04-29 11:10:25", "callsign": "AI4TM", "tg_slot": "91"}, {"time": "2026-04-29 11:10:05", "callsign": "VU2EHB", "tg_slot": "91"}, {"time": "2026-04-29 11:09:33", "callsign": "AI4TM", "tg_slot": "91"}], "system": {"hostname": "pi-star", "uptime": "up 8 weeks, 1 day, 21 hours, 5 minutes", "cpu_load": 0.18, "temperature": "temp=50.5'C", "memory": "152/972 MB", "disk": "4.5G/119G (4%)"}}