[{"time": "2026-03-23 08:09:42", "callsign": "KC9UBS", "tg_slot": "93"}, {"time": "2026-03-23 08:09:19", "callsign": "KJ5EPU", "tg_slot": "93"}, {"time": "2026-03-23 08:08:21", "callsign": "KC9UBS", "tg_slot": "93"}, {"time": "2026-03-23 08:06:56", "callsign": "KJ5EPU", "tg_slot": "93"}, {"time": "2026-03-23 08:06:42", "callsign": "KC9UBS", "tg_slot": "93"}, {"time": "2026-03-23 08:06:31", "callsign": "KJ5EPU", "tg_slot": "93"}, {"time": "2026-03-23 08:06:10", "callsign": "KC9UBS", "tg_slot": "93"}, {"time": "2026-03-23 08:05:50", "callsign": "KJ5EPU", "tg_slot": "93"}, {"time": "2026-03-23 08:05:19", "callsign": "KC9UBS", "tg_slot": "93"}, {"time": "2026-03-23 08:05:02", "callsign": "KJ5EPU", "tg_slot": "93"}, {"time": "2026-03-23 08:04:31", "callsign": "KC9UBS", "tg_slot": "93"}, {"time": "2026-03-23 08:04:01", "callsign": "KJ5EPU", "tg_slot": "93"}, {"time": "2026-03-23 08:03:29", "callsign": "KC9UBS", "tg_slot": "93"}, {"time": "2026-03-23 08:03:15", "callsign": "KC9UBS", "tg_slot": "93"}, {"time": "2026-03-23 08:02:34", "callsign": "KJ5EPU", "tg_slot": "93"}, {"time": "2026-03-23 08:01:44", "callsign": "KC9UBS", "tg_slot": "93"}]