[{"time": "2026-04-01 18:29:56", "callsign": "W9GNW", "tg_slot": "93"}, {"time": "2026-04-01 18:16:12", "callsign": "VE3LC", "tg_slot": "93"}, {"time": "2026-04-01 18:13:43", "callsign": "VE3LC", "tg_slot": "93"}, {"time": "2026-04-01 18:13:27", "callsign": "KR4KBE", "tg_slot": "93"}, {"time": "2026-04-01 18:12:37", "callsign": "VE3LC", "tg_slot": "93"}, {"time": "2026-04-01 18:12:03", "callsign": "VE3LC", "tg_slot": "93"}, {"time": "2026-04-01 18:11:46", "callsign": "KK6AZB", "tg_slot": "93"}, {"time": "2026-04-01 18:11:11", "callsign": "KK6AZB", "tg_slot": "93"}, {"time": "2026-04-01 18:10:48", "callsign": "K2TPT", "tg_slot": "93"}, {"time": "2026-04-01 18:08:00", "callsign": "KN1KSR", "tg_slot": "93"}, {"time": "2026-04-01 18:06:57", "callsign": "KG2MS", "tg_slot": "93"}, {"time": "2026-04-01 18:05:38", "callsign": "KN1KSR", "tg_slot": "93"}, {"time": "2026-04-01 18:04:43", "callsign": "KN1KSR", "tg_slot": "93"}]