{"entries": [{"time": "2026-04-29 18:19:39", "callsign": "MM7KIP", "tg_slot": "91"}, {"time": "2026-04-29 18:18:50", "callsign": "KR4DEM", "tg_slot": "91"}, {"time": "2026-04-29 18:18:07", "callsign": "MM7KIP", "tg_slot": "91"}, {"time": "2026-04-29 18:17:42", "callsign": "KR4DEM", "tg_slot": "91"}, {"time": "2026-04-29 18:17:28", "callsign": "MM7KIP", "tg_slot": "91"}, {"time": "2026-04-29 18:17:02", "callsign": "EA1SS", "tg_slot": "91"}, {"time": "2026-04-29 18:16:39", "callsign": "BH3VAP", "tg_slot": "91"}, {"time": "2026-04-29 18:16:23", "callsign": "KC3DAT", "tg_slot": "91"}, {"time": "2026-04-29 18:16:19", "callsign": "KC8BT", "tg_slot": "91"}, {"time": "2026-04-29 18:16:14", "callsign": "KR4DEM", "tg_slot": "91"}, {"time": "2026-04-29 18:15:44", "callsign": "KC3DAT", "tg_slot": "91"}, {"time": "2026-04-29 18:15:32", "callsign": "KR4DEM", "tg_slot": "91"}, {"time": "2026-04-29 18:15:12", "callsign": "MM7KIP", "tg_slot": "91"}, {"time": "2026-04-29 18:15:06", "callsign": "KC3DAT", "tg_slot": "91"}, {"time": "2026-04-29 18:15:01", "callsign": "DL8BG", "tg_slot": "91"}, {"time": "2026-04-29 18:14:55", "callsign": "DL8BG", "tg_slot": "91"}, {"time": "2026-04-29 18:14:54", "callsign": "KR4DEM", "tg_slot": "91"}, {"time": "2026-04-29 18:14:43", "callsign": "KC3DAT", "tg_slot": "91"}, {"time": "2026-04-29 18:14:35", "callsign": "EA1SS", "tg_slot": "91"}], "system": {"hostname": "pi-star", "uptime": "up 8 weeks, 2 days, 4 hours, 10 minutes", "cpu_load": 0.05, "temperature": "temp=47.8'C", "memory": "152/972 MB", "disk": "4.5G/119G (4%)"}}