{"entries": [{"time": "2026-06-02 16:54:38", "callsign": "G0SRZ", "tg_slot": "93"}, {"time": "2026-06-02 16:52:35", "callsign": "G0SRZ", "tg_slot": "93"}, {"time": "2026-06-02 16:52:26", "callsign": "G0SRZ", "tg_slot": "93"}, {"time": "2026-06-02 16:52:01", "callsign": "N3ZLL", "tg_slot": "93"}, {"time": "2026-06-02 16:51:57", "callsign": "G0SRZ", "tg_slot": "93"}, {"time": "2026-06-02 16:44:54", "callsign": "KK6FU", "tg_slot": "93"}, {"time": "2026-06-02 16:44:50", "callsign": "KK6FU", "tg_slot": "93"}, {"time": "2026-06-02 16:41:49", "callsign": "W9GNW", "tg_slot": "93"}, {"time": "2026-06-02 16:39:50", "callsign": "KM6PS", "tg_slot": "93"}, {"time": "2026-06-02 16:38:59", "callsign": "KK7CXS", "tg_slot": "93"}, {"time": "2026-06-02 16:35:56", "callsign": "KO4AON", "tg_slot": "93"}, {"time": "2026-06-02 16:35:01", "callsign": "KQ4JGF", "tg_slot": "93"}, {"time": "2026-06-02 16:33:16", "callsign": "KO4AON", "tg_slot": "93"}], "system": {"hostname": "pi-star", "uptime": "up 13 weeks, 1 day, 2 hours, 45 minutes", "cpu_load": 0.0, "temperature": "temp=49.4'C", "memory": "151/972 MB", "disk": "4.4G/119G (4%)"}}