{"entries": [{"time": "2026-06-10 11:49:57", "callsign": "AG0J", "tg_slot": "93"}, {"time": "2026-06-10 11:48:08", "callsign": "VK2GAP", "tg_slot": "93"}, {"time": "2026-06-10 11:46:11", "callsign": "VK2GAP", "tg_slot": "93"}, {"time": "2026-06-10 11:33:27", "callsign": "W9YK", "tg_slot": "93"}, {"time": "2026-06-10 11:22:12", "callsign": "KB6RRX", "tg_slot": "93"}, {"time": "2026-06-10 11:22:06", "callsign": "KB6RRX", "tg_slot": "93"}, {"time": "2026-06-10 11:14:50", "callsign": "KB9UPY", "tg_slot": "93"}, {"time": "2026-06-10 11:06:01", "callsign": "W9YK", "tg_slot": "93"}, {"time": "2026-06-10 10:52:40", "callsign": "VK5DP", "tg_slot": "93"}, {"time": "2026-06-10 10:52:23", "callsign": "KD4STT", "tg_slot": "93"}, {"time": "2026-06-10 10:52:11", "callsign": "KD4STT", "tg_slot": "93"}, {"time": "2026-06-10 10:49:37", "callsign": "KQ4ULP", "tg_slot": "6"}], "system": {"hostname": "pi-star", "uptime": "up 14 weeks, 1 day, 21 hours, 40 minutes", "cpu_load": 0.1, "temperature": "temp=50.5'C", "memory": "152/972 MB", "disk": "4.4G/119G (4%)"}}