{"entries": [{"time": "2026-06-01 01:54:22", "callsign": "WK4U", "tg_slot": "93"}, {"time": "2026-06-01 01:52:59", "callsign": "VE7BUL", "tg_slot": "93"}, {"time": "2026-06-01 01:52:41", "callsign": "KO6MPS", "tg_slot": "93"}, {"time": "2026-06-01 01:51:56", "callsign": "KO6MPS", "tg_slot": "93"}, {"time": "2026-06-01 01:45:45", "callsign": "KF0VXJ", "tg_slot": "93"}, {"time": "2026-06-01 01:43:34", "callsign": "KN2B", "tg_slot": "93"}, {"time": "2026-06-01 01:43:30", "callsign": "KN2B", "tg_slot": "93"}, {"time": "2026-06-01 01:43:04", "callsign": "W6AC", "tg_slot": "93"}, {"time": "2026-06-01 01:40:48", "callsign": "WA0VBM", "tg_slot": "93"}, {"time": "2026-06-01 01:40:13", "callsign": "K2TPT", "tg_slot": "93"}, {"time": "2026-06-01 01:36:20", "callsign": "KI5YLQ", "tg_slot": "93"}, {"time": "2026-06-01 01:33:26", "callsign": "K5BUX", "tg_slot": "93"}, {"time": "2026-06-01 01:33:18", "callsign": "K5BUX", "tg_slot": "93"}, {"time": "2026-06-01 01:32:58", "callsign": "K4PTX", "tg_slot": "93"}], "system": {"hostname": "pi-star", "uptime": "up 12 weeks, 6 days, 11 hours, 45 minutes", "cpu_load": 0.0, "temperature": "temp=47.2'C", "memory": "151/972 MB", "disk": "4.4G/119G (4%)"}}