{"entries": [{"time": "2026-04-17 21:49:36", "callsign": "KJ5IRL", "tg_slot": "93"}, {"time": "2026-04-17 21:49:21", "callsign": "KJ5IRL", "tg_slot": "93"}, {"time": "2026-04-17 21:49:16", "callsign": "KJ5IRL", "tg_slot": "93"}, {"time": "2026-04-17 21:45:56", "callsign": "WV5T", "tg_slot": "93"}, {"time": "2026-04-17 21:40:49", "callsign": "M7LYG", "tg_slot": "93"}, {"time": "2026-04-17 21:40:39", "callsign": "M7LYG", "tg_slot": "93"}, {"time": "2026-04-17 21:39:05", "callsign": "PU2LQS", "tg_slot": "93"}, {"time": "2026-04-17 21:34:51", "callsign": "KM7EUR", "tg_slot": "93"}, {"time": "2026-04-17 21:32:23", "callsign": "KR4GXO", "tg_slot": "93"}, {"time": "2026-04-17 21:32:18", "callsign": "KN6YKE", "tg_slot": "93"}, {"time": "2026-04-17 21:31:23", "callsign": "KN6YKE", "tg_slot": "93"}, {"time": "2026-04-17 21:30:31", "callsign": "N5NZZ", "tg_slot": "93"}, {"time": "2026-04-17 21:25:15", "callsign": "M7HYH", "tg_slot": "93"}, {"time": "2026-04-17 21:24:15", "callsign": "M7HYH", "tg_slot": "93"}], "system": {"hostname": "pi-star", "uptime": "up 6 weeks, 4 days, 7 hours, 40 minutes", "cpu_load": 0.03, "temperature": "temp=51.5'C", "memory": "151/972 MB", "disk": "4.4G/119G (4%)"}}