{"entries": [{"time": "2026-05-23 17:29:39", "callsign": "WA2NDV", "tg_slot": "93"}, {"time": "2026-05-23 17:29:09", "callsign": "WA2NDV", "tg_slot": "93"}, {"time": "2026-05-23 17:27:29", "callsign": "AJ6LX", "tg_slot": "6"}, {"time": "2026-05-23 17:27:19", "callsign": "AJ6LX", "tg_slot": "6"}, {"time": "2026-05-23 17:26:56", "callsign": "KN4OUW", "tg_slot": "93"}, {"time": "2026-05-23 17:24:44", "callsign": "W4RKD", "tg_slot": "93"}, {"time": "2026-05-23 17:21:49", "callsign": "KI5MLZ", "tg_slot": "93"}, {"time": "2026-05-23 17:18:45", "callsign": "K2TPT", "tg_slot": "93"}, {"time": "2026-05-23 17:11:47", "callsign": "K2TPT", "tg_slot": "93"}, {"time": "2026-05-23 17:10:01", "callsign": "KI5MLZ", "tg_slot": "93"}, {"time": "2026-05-23 17:07:31", "callsign": "VK3EAN", "tg_slot": "93"}, {"time": "2026-05-23 17:07:10", "callsign": "K2TPT", "tg_slot": "93"}, {"time": "2026-05-23 17:04:41", "callsign": "K1DCT", "tg_slot": "6"}], "system": {"hostname": "pi-star", "uptime": "up 11 weeks, 5 days, 3 hours, 20 minutes", "cpu_load": 0.06, "temperature": "temp=47.2'C", "memory": "151/972 MB", "disk": "4.4G/119G (4%)"}}