{"entries": [{"time": "2026-04-16 22:26:33", "callsign": "AJ4M", "tg_slot": "93"}, {"time": "2026-04-16 22:20:58", "callsign": "KQ4EFZ", "tg_slot": "93"}, {"time": "2026-04-16 22:20:43", "callsign": "N2SPY", "tg_slot": "93"}, {"time": "2026-04-16 22:20:13", "callsign": "KQ4EFZ", "tg_slot": "93"}, {"time": "2026-04-16 22:19:43", "callsign": "KR4AMQ", "tg_slot": "93"}, {"time": "2026-04-16 22:19:25", "callsign": "N1EDF", "tg_slot": "93"}, {"time": "2026-04-16 22:19:01", "callsign": "N1EDF", "tg_slot": "93"}, {"time": "2026-04-16 22:18:51", "callsign": "N1EDF", "tg_slot": "93"}, {"time": "2026-04-16 22:18:07", "callsign": "N1EDF", "tg_slot": "93"}, {"time": "2026-04-16 22:17:53", "callsign": "KR4AMQ", "tg_slot": "93"}, {"time": "2026-04-16 22:15:57", "callsign": "AI1K", "tg_slot": "93"}, {"time": "2026-04-16 22:15:49", "callsign": "AI1K", "tg_slot": "93"}, {"time": "2026-04-16 22:13:35", "callsign": "AI1K", "tg_slot": "93"}], "system": {"hostname": "pi-star", "uptime": "up 6 weeks, 3 days, 8 hours, 20 minutes", "cpu_load": 0.0, "temperature": "temp=52.6'C", "memory": "151/972 MB", "disk": "4.4G/119G (4%)"}}