{"entries": [{"time": "2026-04-23 00:59:03", "callsign": "KD8BNS", "tg_slot": "93"}, {"time": "2026-04-23 00:58:27", "callsign": "K1NR", "tg_slot": "6"}, {"time": "2026-04-23 00:55:55", "callsign": "KK6AZB", "tg_slot": "93"}, {"time": "2026-04-23 00:55:17", "callsign": "KK6AZB", "tg_slot": "93"}, {"time": "2026-04-23 00:49:16", "callsign": "KF5LIC", "tg_slot": "93"}, {"time": "2026-04-23 00:47:08", "callsign": "NF8F", "tg_slot": "93"}, {"time": "2026-04-23 00:45:23", "callsign": "KB9UPY", "tg_slot": "93"}, {"time": "2026-04-23 00:33:57", "callsign": "KC1RAY", "tg_slot": "6"}, {"time": "2026-04-23 00:32:45", "callsign": "N1JET", "tg_slot": "6"}, {"time": "2026-04-23 00:32:33", "callsign": "KC1RAY", "tg_slot": "6"}, {"time": "2026-04-23 00:32:06", "callsign": "N1JET", "tg_slot": "6"}, {"time": "2026-04-23 00:31:35", "callsign": "KC1RAY", "tg_slot": "6"}, {"time": "2026-04-23 00:30:47", "callsign": "N1JET", "tg_slot": "6"}], "system": {"hostname": "pi-star", "uptime": "up 7 weeks, 2 days, 10 hours, 50 minutes", "cpu_load": 0.0, "temperature": "temp=49.4'C", "memory": "151/972 MB", "disk": "4.5G/119G (4%)"}}