[{"time": "2026-03-26 17:13:08", "callsign": "WB0QMR", "tg_slot": "93"}, {"time": "2026-03-26 17:11:29", "callsign": "WB0QMR", "tg_slot": "93"}, {"time": "2026-03-26 17:11:09", "callsign": "WB0QMR", "tg_slot": "93"}, {"time": "2026-03-26 17:08:30", "callsign": "N1OMG", "tg_slot": "93"}, {"time": "2026-03-26 17:08:10", "callsign": "N1OMG", "tg_slot": "93"}, {"time": "2026-03-26 17:07:51", "callsign": "IN3GID", "tg_slot": "93"}, {"time": "2026-03-26 17:07:31", "callsign": "N1OMG", "tg_slot": "93"}, {"time": "2026-03-26 17:07:05", "callsign": "IN3GID", "tg_slot": "93"}, {"time": "2026-03-26 17:06:44", "callsign": "N1OMG", "tg_slot": "93"}, {"time": "2026-03-26 17:06:22", "callsign": "IN3GID", "tg_slot": "93"}, {"time": "2026-03-26 17:05:54", "callsign": "N1OMG", "tg_slot": "93"}, {"time": "2026-03-26 17:05:37", "callsign": "F4MNX", "tg_slot": "93"}, {"time": "2026-03-26 17:05:19", "callsign": "IN3GID", "tg_slot": "93"}, {"time": "2026-03-26 17:04:32", "callsign": "IN3GID", "tg_slot": "93"}, {"time": "2026-03-26 17:04:26", "callsign": "N1OMG", "tg_slot": "93"}, {"time": "2026-03-26 17:03:52", "callsign": "IN3GID", "tg_slot": "93"}, {"time": "2026-03-26 17:03:10", "callsign": "N1OMG", "tg_slot": "93"}, {"time": "2026-03-26 17:02:45", "callsign": "IN3GID", "tg_slot": "93"}, {"time": "2026-03-26 17:02:15", "callsign": "N1OMG", "tg_slot": "93"}]