{"entries": [{"time": "2026-05-27 01:39:33", "callsign": "KE2IMU", "tg_slot": "93"}, {"time": "2026-05-27 01:37:12", "callsign": "KO1C", "tg_slot": "6"}, {"time": "2026-05-27 01:36:00", "callsign": "KC1DCZ", "tg_slot": "6"}, {"time": "2026-05-27 01:35:51", "callsign": "KA1GWL", "tg_slot": "6"}, {"time": "2026-05-27 01:35:24", "callsign": "KC1DCZ", "tg_slot": "6"}, {"time": "2026-05-27 01:34:28", "callsign": "KA1GWL", "tg_slot": "6"}, {"time": "2026-05-27 01:33:43", "callsign": "KC1DCZ", "tg_slot": "6"}, {"time": "2026-05-27 01:33:14", "callsign": "KA1GWL", "tg_slot": "6"}, {"time": "2026-05-27 01:31:45", "callsign": "KC1DCZ", "tg_slot": "6"}, {"time": "2026-05-27 01:31:09", "callsign": "KA1GWL", "tg_slot": "6"}, {"time": "2026-05-27 01:30:17", "callsign": "KC1DCZ", "tg_slot": "6"}, {"time": "2026-05-27 01:29:41", "callsign": "KA1GWL", "tg_slot": "6"}, {"time": "2026-05-27 01:28:25", "callsign": "KC1DCZ", "tg_slot": "6"}, {"time": "2026-05-27 01:27:28", "callsign": "KA1GWL", "tg_slot": "6"}, {"time": "2026-05-27 01:26:50", "callsign": "KC1DCZ", "tg_slot": "6"}, {"time": "2026-05-27 01:26:17", "callsign": "KA1GWL", "tg_slot": "6"}, {"time": "2026-05-27 01:25:07", "callsign": "KC1DCZ", "tg_slot": "6"}, {"time": "2026-05-27 01:24:26", "callsign": "KA1GWL", "tg_slot": "6"}, {"time": "2026-05-27 01:23:24", "callsign": "KC1DCZ", "tg_slot": "6"}, {"time": "2026-05-27 01:23:01", "callsign": "KA1GWL", "tg_slot": "6"}, {"time": "2026-05-27 01:22:27", "callsign": "KC1DCZ", "tg_slot": "6"}], "system": {"hostname": "pi-star", "uptime": "up 12 weeks, 1 day, 11 hours, 30 minutes", "cpu_load": 0.04, "temperature": "temp=49.4'C", "memory": "152/972 MB", "disk": "4.4G/119G (4%)"}}