{"entries": [{"time": "2026-04-30 06:19:37", "callsign": "WP4TWS", "tg_slot": "91"}, {"time": "2026-04-30 06:19:04", "callsign": "DN9HL", "tg_slot": "91"}, {"time": "2026-04-30 06:18:26", "callsign": "WP4TWS", "tg_slot": "91"}, {"time": "2026-04-30 06:18:16", "callsign": "DN9HL", "tg_slot": "91"}, {"time": "2026-04-30 06:18:06", "callsign": "KI4PHP", "tg_slot": "91"}, {"time": "2026-04-30 06:18:04", "callsign": "WP4TWS", "tg_slot": "91"}, {"time": "2026-04-30 06:17:49", "callsign": "VU2EHB", "tg_slot": "91"}, {"time": "2026-04-30 06:17:29", "callsign": "WP4TWS", "tg_slot": "91"}, {"time": "2026-04-30 06:17:00", "callsign": "VU2EHB", "tg_slot": "91"}, {"time": "2026-04-30 06:16:18", "callsign": "WP4TWS", "tg_slot": "91"}, {"time": "2026-04-30 06:16:01", "callsign": "VU2EHB", "tg_slot": "91"}, {"time": "2026-04-30 06:15:46", "callsign": "WP4TWS", "tg_slot": "91"}, {"time": "2026-04-30 06:15:32", "callsign": "EB1HXI", "tg_slot": "91"}, {"time": "2026-04-30 06:15:23", "callsign": "WP4TWS", "tg_slot": "91"}, {"time": "2026-04-30 06:14:57", "callsign": "EB1HXI", "tg_slot": "91"}, {"time": "2026-04-30 06:14:43", "callsign": "EB1HXI", "tg_slot": "91"}], "system": {"hostname": "pi-star", "uptime": "up 8 weeks, 2 days, 16 hours, 10 minutes", "cpu_load": 0.05, "temperature": "temp=47.8'C", "memory": "152/972 MB", "disk": "4.5G/119G (4%)"}}