{"entries": [{"time": "2026-04-26 06:14:28", "callsign": "DO1LVS", "tg_slot": "91"}, {"time": "2026-04-26 06:12:46", "callsign": "SP2GKW", "tg_slot": "91"}, {"time": "2026-04-26 06:12:30", "callsign": "6K2MAU", "tg_slot": "91"}, {"time": "2026-04-26 06:12:09", "callsign": "6K2MAU", "tg_slot": "91"}, {"time": "2026-04-26 06:11:48", "callsign": "SP8STB", "tg_slot": "91"}, {"time": "2026-04-26 06:11:38", "callsign": "SP8STB", "tg_slot": "91"}, {"time": "2026-04-26 06:11:05", "callsign": "IN3GID", "tg_slot": "91"}, {"time": "2026-04-26 06:10:32", "callsign": "JK1GWB", "tg_slot": "91"}, {"time": "2026-04-26 06:10:24", "callsign": "KN4PPD", "tg_slot": "91"}, {"time": "2026-04-26 06:10:01", "callsign": "YO2DA", "tg_slot": "91"}, {"time": "2026-04-26 06:09:06", "callsign": "KN6UGX", "tg_slot": "91"}, {"time": "2026-04-26 06:08:35", "callsign": "W1CDO", "tg_slot": "91"}, {"time": "2026-04-26 06:08:27", "callsign": "IN3GID", "tg_slot": "91"}, {"time": "2026-04-26 06:07:53", "callsign": "IN3GID", "tg_slot": "91"}, {"time": "2026-04-26 06:07:20", "callsign": "VU2YOR", "tg_slot": "91"}, {"time": "2026-04-26 06:07:14", "callsign": "TI2JV", "tg_slot": "91"}], "system": {"hostname": "pi-star", "uptime": "up 7 weeks, 5 days, 16 hours, 5 minutes", "cpu_load": 0.0, "temperature": "temp=48.3'C", "memory": "151/972 MB", "disk": "4.5G/119G (4%)"}}