[{"time": "2026-03-14 10:20:23", "callsign": "KB9UPY", "tg_slot": "93"}, {"time": "2026-03-14 10:05:53", "callsign": "IZ5WSR", "tg_slot": "93"}, {"time": "2026-03-14 10:05:27", "callsign": "KK6AZB", "tg_slot": "93"}, {"time": "2026-03-14 10:05:07", "callsign": "IZ5WSR", "tg_slot": "93"}, {"time": "2026-03-14 10:04:33", "callsign": "KK6AZB", "tg_slot": "93"}, {"time": "2026-03-14 10:03:58", "callsign": "IZ5WSR", "tg_slot": "93"}, {"time": "2026-03-14 10:03:24", "callsign": "KK6AZB", "tg_slot": "93"}, {"time": "2026-03-14 10:03:16", "callsign": "IZ5WSR", "tg_slot": "93"}, {"time": "2026-03-14 10:02:47", "callsign": "KK6AZB", "tg_slot": "93"}, {"time": "2026-03-14 10:02:32", "callsign": "IZ5WSR", "tg_slot": "93"}, {"time": "2026-03-14 10:02:06", "callsign": "KK6AZB", "tg_slot": "93"}, {"time": "2026-03-14 10:01:37", "callsign": "KK6AZB", "tg_slot": "93"}, {"time": "2026-03-14 09:52:31", "callsign": "N4WPK", "tg_slot": "93"}, {"time": "2026-03-14 09:50:28", "callsign": "IN3GID", "tg_slot": "93"}, {"time": "2026-03-14 09:50:19", "callsign": "IZ5WSR", "tg_slot": "93"}]