{"entries": [{"time": "2026-04-12 00:24:55", "callsign": "W1VM", "tg_slot": "93"}, {"time": "2026-04-12 00:24:30", "callsign": "KD3BHM", "tg_slot": "93"}, {"time": "2026-04-12 00:24:15", "callsign": "W1VM", "tg_slot": "93"}, {"time": "2026-04-12 00:23:47", "callsign": "KD3BHM", "tg_slot": "93"}, {"time": "2026-04-12 00:23:28", "callsign": "W1VM", "tg_slot": "93"}, {"time": "2026-04-12 00:23:17", "callsign": "KD3BHM", "tg_slot": "93"}, {"time": "2026-04-12 00:23:08", "callsign": "W1VM", "tg_slot": "93"}, {"time": "2026-04-12 00:22:50", "callsign": "KD3BHM", "tg_slot": "93"}, {"time": "2026-04-12 00:22:37", "callsign": "W1VM", "tg_slot": "93"}, {"time": "2026-04-12 00:22:21", "callsign": "KC1UHT", "tg_slot": "93"}, {"time": "2026-04-12 00:22:13", "callsign": "KD3BHM", "tg_slot": "93"}, {"time": "2026-04-12 00:22:02", "callsign": "W1VM", "tg_slot": "93"}, {"time": "2026-04-12 00:20:49", "callsign": "W1VM", "tg_slot": "93"}, {"time": "2026-04-12 00:18:24", "callsign": "KF8FIW", "tg_slot": "93"}, {"time": "2026-04-12 00:17:31", "callsign": "KD3BHM", "tg_slot": "93"}, {"time": "2026-04-12 00:17:07", "callsign": "VE4ZWR", "tg_slot": "93"}], "system": {"hostname": "pi-star", "uptime": "up 5 weeks, 5 days, 10 hours, 15 minutes", "cpu_load": 0.1, "temperature": "temp=49.9'C", "memory": "151/972 MB", "disk": "4.4G/119G (4%)"}}