{"entries": [{"time": "2026-04-23 02:27:03", "callsign": "KI5DRV", "tg_slot": "93"}, {"time": "2026-04-23 02:25:32", "callsign": "N2SPY", "tg_slot": "93"}, {"time": "2026-04-23 02:22:05", "callsign": "KB1KWY", "tg_slot": "93"}, {"time": "2026-04-23 02:21:45", "callsign": "KE9FFG", "tg_slot": "93"}, {"time": "2026-04-23 02:16:25", "callsign": "K3JSJ", "tg_slot": "93"}, {"time": "2026-04-23 02:15:13", "callsign": "KE9FFG", "tg_slot": "93"}, {"time": "2026-04-23 02:11:17", "callsign": "K3LTA", "tg_slot": "93"}, {"time": "2026-04-23 02:08:40", "callsign": "KB2MPX", "tg_slot": "93"}, {"time": "2026-04-23 02:01:29", "callsign": "K4OZI", "tg_slot": "93"}, {"time": "2026-04-23 01:58:36", "callsign": "KN6IYG", "tg_slot": "93"}, {"time": "2026-04-23 01:58:16", "callsign": "KN6IYG", "tg_slot": "93"}], "system": {"hostname": "pi-star", "uptime": "up 7 weeks, 2 days, 12 hours, 20 minutes", "cpu_load": 0.08, "temperature": "temp=49.9'C", "memory": "150/972 MB", "disk": "4.5G/119G (4%)"}}