{"entries": [{"time": "2026-06-10 23:42:41", "callsign": "KR4GZZ", "tg_slot": "93"}, {"time": "2026-06-10 23:42:21", "callsign": "KR4GZZ", "tg_slot": "93"}, {"time": "2026-06-10 23:34:56", "callsign": "AJ6LN", "tg_slot": "93"}, {"time": "2026-06-10 23:31:59", "callsign": "KF6REU", "tg_slot": "93"}, {"time": "2026-06-10 23:30:51", "callsign": "KR4GZZ", "tg_slot": "93"}, {"time": "2026-06-10 23:22:01", "callsign": "KI6NKZ", "tg_slot": "93"}, {"time": "2026-06-10 23:21:00", "callsign": "N6BSD", "tg_slot": "93"}, {"time": "2026-06-10 23:19:33", "callsign": "KQ4YTL", "tg_slot": "93"}, {"time": "2026-06-10 23:17:56", "callsign": "K2MWS", "tg_slot": "93"}, {"time": "2026-06-10 23:17:44", "callsign": "K2MWS", "tg_slot": "93"}, {"time": "2026-06-10 23:14:37", "callsign": "KR4HHT", "tg_slot": "93"}], "system": {"hostname": "pi-star", "uptime": "up 14 weeks, 2 days, 9 hours, 40 minutes", "cpu_load": 0.07, "temperature": "temp=51.5'C", "memory": "152/972 MB", "disk": "4.4G/119G (4%)"}}