{"entries": [{"time": "2026-04-11 16:39:34", "callsign": "HS0ZRA", "tg_slot": "93"}, {"time": "2026-04-11 16:37:30", "callsign": "IN3GID", "tg_slot": "93"}, {"time": "2026-04-11 16:36:16", "callsign": "K8WGP", "tg_slot": "93"}, {"time": "2026-04-11 16:36:12", "callsign": "HS0ZRA", "tg_slot": "93"}, {"time": "2026-04-11 16:35:55", "callsign": "IN3GID", "tg_slot": "93"}, {"time": "2026-04-11 16:35:47", "callsign": "KF4FYX", "tg_slot": "93"}, {"time": "2026-04-11 16:35:20", "callsign": "IN3GID", "tg_slot": "93"}, {"time": "2026-04-11 16:34:10", "callsign": "KF4FYX", "tg_slot": "93"}, {"time": "2026-04-11 16:33:32", "callsign": "IN3GID", "tg_slot": "93"}, {"time": "2026-04-11 16:32:28", "callsign": "KF4FYX", "tg_slot": "93"}, {"time": "2026-04-11 16:31:59", "callsign": "IN3GID", "tg_slot": "93"}, {"time": "2026-04-11 16:31:17", "callsign": "KF4FYX", "tg_slot": "93"}, {"time": "2026-04-11 16:30:20", "callsign": "HS0ZRA", "tg_slot": "93"}, {"time": "2026-04-11 16:30:02", "callsign": "IN3GID", "tg_slot": "93"}, {"time": "2026-04-11 16:29:11", "callsign": "KF4FYX", "tg_slot": "93"}, {"time": "2026-04-11 16:28:50", "callsign": "KR4KBE", "tg_slot": "93"}, {"time": "2026-04-11 16:28:12", "callsign": "W2AH", "tg_slot": "93"}], "system": {"hostname": "pi-star", "uptime": "up 5 weeks, 5 days, 2 hours, 30 minutes", "cpu_load": 0.02, "temperature": "temp=49.4'C", "memory": "151/972 MB", "disk": "4.4G/119G (4%)"}}