{"entries": [{"time": "2026-06-08 23:38:57", "callsign": "K2TPT", "tg_slot": "93"}, {"time": "2026-06-08 23:38:30", "callsign": "W8NCA", "tg_slot": "93"}, {"time": "2026-06-08 23:33:59", "callsign": "KE2BPN", "tg_slot": "93"}, {"time": "2026-06-08 23:32:31", "callsign": "W1VM", "tg_slot": "93"}, {"time": "2026-06-08 23:32:05", "callsign": "W1VM", "tg_slot": "93"}, {"time": "2026-06-08 23:31:35", "callsign": "KR4KFE", "tg_slot": "93"}, {"time": "2026-06-08 23:31:20", "callsign": "KR4KFE", "tg_slot": "93"}, {"time": "2026-06-08 23:26:14", "callsign": "KR9K", "tg_slot": "93"}, {"time": "2026-06-08 23:26:01", "callsign": "KR9K", "tg_slot": "93"}, {"time": "2026-06-08 23:25:56", "callsign": "KR9K", "tg_slot": "93"}, {"time": "2026-06-08 23:25:50", "callsign": "KR9K", "tg_slot": "93"}, {"time": "2026-06-08 23:25:35", "callsign": "KR9K", "tg_slot": "93"}, {"time": "2026-06-08 23:25:10", "callsign": "KR9K", "tg_slot": "93"}, {"time": "2026-06-08 23:25:02", "callsign": "KR9K", "tg_slot": "93"}], "system": {"hostname": "pi-star", "uptime": "up 14 weeks, 9 hours, 30 minutes", "cpu_load": 0.13, "temperature": "temp=50.5'C", "memory": "151/972 MB", "disk": "4.4G/119G (4%)"}}