{"entries": [{"time": "2026-06-03 20:09:51", "callsign": "KD1TF", "tg_slot": "6"}, {"time": "2026-06-03 20:09:21", "callsign": "KD1TF", "tg_slot": "6"}, {"time": "2026-06-03 20:08:51", "callsign": "KD1TF", "tg_slot": "6"}, {"time": "2026-06-03 20:08:21", "callsign": "KD1TF", "tg_slot": "6"}, {"time": "2026-06-03 20:07:51", "callsign": "KD1TF", "tg_slot": "6"}, {"time": "2026-06-03 20:07:21", "callsign": "KD1TF", "tg_slot": "6"}, {"time": "2026-06-03 20:07:06", "callsign": "K1RPD", "tg_slot": "6"}, {"time": "2026-06-03 20:06:51", "callsign": "KD1TF", "tg_slot": "6"}, {"time": "2026-06-03 20:06:39", "callsign": "K1RPD", "tg_slot": "6"}, {"time": "2026-06-03 20:06:20", "callsign": "KD1TF", "tg_slot": "6"}, {"time": "2026-06-03 20:05:50", "callsign": "KD1TF", "tg_slot": "6"}, {"time": "2026-06-03 20:05:20", "callsign": "KD1TF", "tg_slot": "6"}, {"time": "2026-06-03 20:04:50", "callsign": "KD1TF", "tg_slot": "6"}, {"time": "2026-06-03 20:04:45", "callsign": "K1RPD", "tg_slot": "6"}, {"time": "2026-06-03 20:04:44", "callsign": "K1RPD", "tg_slot": "6"}, {"time": "2026-06-03 20:04:20", "callsign": "KD1TF", "tg_slot": "6"}], "system": {"hostname": "pi-star", "uptime": "up 13 weeks, 2 days, 6 hours", "cpu_load": 0.07, "temperature": "temp=48.9'C", "memory": "151/972 MB", "disk": "4.4G/119G (4%)"}}