{"entries": [{"time": "2026-04-18 18:34:30", "callsign": "N8CQD", "tg_slot": "93"}, {"time": "2026-04-18 18:34:23", "callsign": "AI4WZ", "tg_slot": "93"}, {"time": "2026-04-18 18:34:20", "callsign": "W4RKD", "tg_slot": "93"}, {"time": "2026-04-18 18:34:03", "callsign": "N8CQD", "tg_slot": "93"}, {"time": "2026-04-18 18:33:37", "callsign": "W4RKD", "tg_slot": "93"}, {"time": "2026-04-18 18:33:22", "callsign": "N8CQD", "tg_slot": "93"}, {"time": "2026-04-18 18:32:52", "callsign": "W4RKD", "tg_slot": "93"}, {"time": "2026-04-18 18:32:31", "callsign": "N8CQD", "tg_slot": "93"}, {"time": "2026-04-18 18:32:11", "callsign": "W4RKD", "tg_slot": "93"}, {"time": "2026-04-18 18:32:05", "callsign": "N8CQD", "tg_slot": "93"}, {"time": "2026-04-18 18:31:39", "callsign": "N8CQD", "tg_slot": "93"}, {"time": "2026-04-18 18:31:18", "callsign": "N8CQD", "tg_slot": "93"}, {"time": "2026-04-18 18:30:59", "callsign": "KR4GPH", "tg_slot": "93"}, {"time": "2026-04-18 18:29:53", "callsign": "KC4KIN", "tg_slot": "93"}, {"time": "2026-04-18 18:28:16", "callsign": "N8CQD", "tg_slot": "93"}, {"time": "2026-04-18 18:27:21", "callsign": "KK6JNI", "tg_slot": "93"}, {"time": "2026-04-18 18:26:02", "callsign": "KR4EGS", "tg_slot": "93"}, {"time": "2026-04-18 18:25:17", "callsign": "N8CQD", "tg_slot": "93"}], "system": {"hostname": "pi-star", "uptime": "up 6 weeks, 5 days, 4 hours, 25 minutes", "cpu_load": 0.0, "temperature": "temp=50.5'C", "memory": "151/972 MB", "disk": "4.4G/119G (4%)"}}