{"entries": [{"time": "2026-04-13 22:59:52", "callsign": "KB7ZZ", "tg_slot": "93"}, {"time": "2026-04-13 22:59:42", "callsign": "KB7ZZ", "tg_slot": "93"}, {"time": "2026-04-13 22:59:17", "callsign": "KB7ZZ", "tg_slot": "93"}, {"time": "2026-04-13 22:58:51", "callsign": "KC9UZR", "tg_slot": "93"}, {"time": "2026-04-13 22:58:24", "callsign": "KC1SJS", "tg_slot": "6"}, {"time": "2026-04-13 22:57:22", "callsign": "K8RAR", "tg_slot": "93"}, {"time": "2026-04-13 22:56:20", "callsign": "AB7P", "tg_slot": "93"}, {"time": "2026-04-13 22:55:47", "callsign": "AB7P", "tg_slot": "93"}, {"time": "2026-04-13 22:51:17", "callsign": "W1RAC", "tg_slot": "6"}, {"time": "2026-04-13 22:50:51", "callsign": "KD4IBD", "tg_slot": "93"}, {"time": "2026-04-13 22:50:03", "callsign": "KQ4GVI", "tg_slot": "93"}, {"time": "2026-04-13 22:47:21", "callsign": "KQ4GVI", "tg_slot": "93"}, {"time": "2026-04-13 22:35:17", "callsign": "W1RAC", "tg_slot": "6"}], "system": {"hostname": "pi-star", "uptime": "up 6 weeks, 8 hours, 50 minutes", "cpu_load": 0.04, "temperature": "temp=51.0'C", "memory": "151/972 MB", "disk": "4.4G/119G (4%)"}}