[{"time": "2026-03-13 17:05:50", "callsign": "KE0CBT", "tg_slot": "93"}, {"time": "2026-03-13 16:58:19", "callsign": "KE4LNG", "tg_slot": "93"}, {"time": "2026-03-13 16:56:22", "callsign": "KD4IRB", "tg_slot": "93"}, {"time": "2026-03-13 16:55:22", "callsign": "KF4FYX", "tg_slot": "93"}, {"time": "2026-03-13 16:50:38", "callsign": "VA3PLJ", "tg_slot": "93"}, {"time": "2026-03-13 16:50:11", "callsign": "VA3PLJ", "tg_slot": "93"}, {"time": "2026-03-13 16:49:41", "callsign": "KM7BYN", "tg_slot": "93"}, {"time": "2026-03-13 16:41:45", "callsign": "KK7CXS", "tg_slot": "93"}, {"time": "2026-03-13 16:41:24", "callsign": "KR4BFV", "tg_slot": "93"}, {"time": "2026-03-13 16:39:19", "callsign": "KE0CBT", "tg_slot": "93"}, {"time": "2026-03-13 16:37:57", "callsign": "KF0VRT", "tg_slot": "93"}, {"time": "2026-03-13 16:37:12", "callsign": "KC1VPB", "tg_slot": "93"}]