{"entries": [{"time": "2026-05-30 17:19:39", "callsign": "EA7AAR", "tg_slot": "93"}, {"time": "2026-05-30 17:18:51", "callsign": "KD5RFG", "tg_slot": "93"}, {"time": "2026-05-30 17:18:44", "callsign": "K6SDZ", "tg_slot": "93"}, {"time": "2026-05-30 17:15:20", "callsign": "EA7AAR", "tg_slot": "93"}, {"time": "2026-05-30 17:14:54", "callsign": "W4RKD", "tg_slot": "93"}, {"time": "2026-05-30 17:14:41", "callsign": "EA7AAR", "tg_slot": "93"}, {"time": "2026-05-30 17:14:13", "callsign": "W4RKD", "tg_slot": "93"}, {"time": "2026-05-30 17:14:00", "callsign": "EA7AAR", "tg_slot": "93"}, {"time": "2026-05-30 17:13:46", "callsign": "W4RKD", "tg_slot": "93"}, {"time": "2026-05-30 17:13:37", "callsign": "W4RKD", "tg_slot": "93"}, {"time": "2026-05-30 17:12:47", "callsign": "KK7CXS", "tg_slot": "93"}, {"time": "2026-05-30 17:10:12", "callsign": "EA7AAR", "tg_slot": "93"}, {"time": "2026-05-30 17:10:07", "callsign": "EA1BDV", "tg_slot": "93"}, {"time": "2026-05-30 17:09:20", "callsign": "EA7AAR", "tg_slot": "93"}, {"time": "2026-05-30 17:08:41", "callsign": "EA1BDV", "tg_slot": "93"}], "system": {"hostname": "pi-star", "uptime": "up 12 weeks, 5 days, 3 hours, 10 minutes", "cpu_load": 0.13, "temperature": "temp=48.3'C", "memory": "151/972 MB", "disk": "4.4G/119G (4%)"}}