{"entries": [{"time": "2026-04-11 17:49:45", "callsign": "3223707", "tg_slot": "93"}, {"time": "2026-04-11 17:49:34", "callsign": "AI4WZ", "tg_slot": "93"}, {"time": "2026-04-11 17:49:03", "callsign": "KB7EAL", "tg_slot": "93"}, {"time": "2026-04-11 17:48:45", "callsign": "K1BES", "tg_slot": "93"}, {"time": "2026-04-11 17:48:34", "callsign": "EA7AAR", "tg_slot": "93"}, {"time": "2026-04-11 17:48:22", "callsign": "K1BES", "tg_slot": "93"}, {"time": "2026-04-11 17:48:02", "callsign": "EA7AAR", "tg_slot": "93"}, {"time": "2026-04-11 17:47:38", "callsign": "K1BES", "tg_slot": "93"}, {"time": "2026-04-11 17:47:19", "callsign": "AB2OQ", "tg_slot": "93"}, {"time": "2026-04-11 17:47:13", "callsign": "EA4AKC", "tg_slot": "93"}, {"time": "2026-04-11 17:47:12", "callsign": "EA7AAR", "tg_slot": "93"}, {"time": "2026-04-11 17:46:47", "callsign": "KF0GBZ", "tg_slot": "93"}, {"time": "2026-04-11 17:46:46", "callsign": "K1BES", "tg_slot": "93"}, {"time": "2026-04-11 17:46:36", "callsign": "K8WGP", "tg_slot": "93"}, {"time": "2026-04-11 17:46:25", "callsign": "EA7AAR", "tg_slot": "93"}, {"time": "2026-04-11 17:46:14", "callsign": "K1BES", "tg_slot": "93"}, {"time": "2026-04-11 17:46:02", "callsign": "IN3GID", "tg_slot": "93"}], "system": {"hostname": "pi-star", "uptime": "up 5 weeks, 5 days, 3 hours, 40 minutes", "cpu_load": 0.12, "temperature": "temp=49.9'C", "memory": "151/972 MB", "disk": "4.4G/119G (4%)"}}