[{"time": "2026-03-30 23:12:02", "callsign": "M6JYP", "tg_slot": "93"}, {"time": "2026-03-30 23:09:55", "callsign": "N9DWN", "tg_slot": "93"}, {"time": "2026-03-30 23:08:58", "callsign": "LU9DKU", "tg_slot": "93"}, {"time": "2026-03-30 23:08:33", "callsign": "LU9DKU", "tg_slot": "93"}, {"time": "2026-03-30 23:02:08", "callsign": "W1VM", "tg_slot": "93"}, {"time": "2026-03-30 23:01:00", "callsign": "KO4SIY", "tg_slot": "93"}, {"time": "2026-03-30 23:00:42", "callsign": "KQ4UON", "tg_slot": "93"}, {"time": "2026-03-30 22:59:55", "callsign": "W1VM", "tg_slot": "93"}, {"time": "2026-03-30 22:57:20", "callsign": "W1VM", "tg_slot": "93"}, {"time": "2026-03-30 22:56:50", "callsign": "KE2AJO", "tg_slot": "93"}, {"time": "2026-03-30 22:56:36", "callsign": "KB9UPY", "tg_slot": "93"}, {"time": "2026-03-30 22:56:17", "callsign": "KD8BNS", "tg_slot": "93"}, {"time": "2026-03-30 22:56:12", "callsign": "KD8BNS", "tg_slot": "93"}, {"time": "2026-03-30 22:53:12", "callsign": "NA9Y", "tg_slot": "93"}]