{"entries": [{"time": "2026-04-25 00:54:46", "callsign": "W1TAT", "tg_slot": "6"}, {"time": "2026-04-25 00:53:53", "callsign": "N1PTX", "tg_slot": "6"}, {"time": "2026-04-25 00:53:14", "callsign": "N1PTX", "tg_slot": "6"}, {"time": "2026-04-25 00:52:41", "callsign": "N1PTX", "tg_slot": "6"}, {"time": "2026-04-25 00:52:05", "callsign": "W1TAT", "tg_slot": "6"}, {"time": "2026-04-25 00:51:28", "callsign": "WO1VES", "tg_slot": "6"}, {"time": "2026-04-25 00:51:22", "callsign": "KC1VAX", "tg_slot": "6"}, {"time": "2026-04-25 00:51:20", "callsign": "WO1VES", "tg_slot": "6"}, {"time": "2026-04-25 00:51:08", "callsign": "W1TAT", "tg_slot": "6"}, {"time": "2026-04-25 00:50:58", "callsign": "KC1VAX", "tg_slot": "6"}, {"time": "2026-04-25 00:50:49", "callsign": "WO1VES", "tg_slot": "6"}, {"time": "2026-04-25 00:49:57", "callsign": "KC1VAX", "tg_slot": "6"}, {"time": "2026-04-25 00:49:52", "callsign": "WO1VES", "tg_slot": "6"}, {"time": "2026-04-25 00:48:23", "callsign": "KC1VAX", "tg_slot": "6"}, {"time": "2026-04-25 00:48:21", "callsign": "W1TAT", "tg_slot": "6"}, {"time": "2026-04-25 00:48:07", "callsign": "W1TAT", "tg_slot": "6"}, {"time": "2026-04-25 00:47:12", "callsign": "WO1VES", "tg_slot": "6"}, {"time": "2026-04-25 00:47:07", "callsign": "N1NTM", "tg_slot": "6"}, {"time": "2026-04-25 00:46:50", "callsign": "W1TAT", "tg_slot": "6"}, {"time": "2026-04-25 00:46:46", "callsign": "W1TAT", "tg_slot": "6"}, {"time": "2026-04-25 00:46:10", "callsign": "KC1VAX", "tg_slot": "6"}], "system": {"hostname": "pi-star", "uptime": "up 7 weeks, 4 days, 10 hours, 45 minutes", "cpu_load": 0.12, "temperature": "temp=49.9'C", "memory": "151/972 MB", "disk": "4.5G/119G (4%)"}}