{"entries": [{"time": "2026-05-13 13:54:35", "callsign": "DN9DDD", "tg_slot": "91"}, {"time": "2026-05-13 13:54:26", "callsign": "VU2EHB", "tg_slot": "91"}, {"time": "2026-05-13 13:54:16", "callsign": "DN9DDD", "tg_slot": "91"}, {"time": "2026-05-13 13:53:51", "callsign": "VU2EHB", "tg_slot": "91"}, {"time": "2026-05-13 13:53:43", "callsign": "DN9HL", "tg_slot": "91"}, {"time": "2026-05-13 13:53:17", "callsign": "DN9HL", "tg_slot": "91"}, {"time": "2026-05-13 13:53:14", "callsign": "VU2EHB", "tg_slot": "91"}, {"time": "2026-05-13 13:52:39", "callsign": "DN9HL", "tg_slot": "91"}, {"time": "2026-05-13 13:51:58", "callsign": "VU2EHB", "tg_slot": "91"}, {"time": "2026-05-13 13:51:35", "callsign": "DN9HL", "tg_slot": "91"}, {"time": "2026-05-13 13:51:16", "callsign": "DN9DDD", "tg_slot": "91"}, {"time": "2026-05-13 13:51:02", "callsign": "DN9HL", "tg_slot": "91"}, {"time": "2026-05-13 13:50:53", "callsign": "VU2EHB", "tg_slot": "91"}, {"time": "2026-05-13 13:50:43", "callsign": "YV5VGA", "tg_slot": "91"}, {"time": "2026-05-13 13:50:30", "callsign": "IU0VIZ", "tg_slot": "91"}], "system": {"hostname": "pi-star", "uptime": "up 10 weeks, 1 day, 23 hours, 45 minutes", "cpu_load": 0.07, "temperature": "temp=49.4'C", "memory": "151/972 MB", "disk": "4.5G/119G (4%)"}}